testing_project/__init__.py
testing_project/cli.py
testing_project/testing_project.py
testing_project-0.1.2.dist-info/AUTHORS.rst
testing_project-0.1.2.dist-info/LICENSE
testing_project-0.1.2.dist-info/METADATA
testing_project-0.1.2.dist-info/WHEEL
testing_project-0.1.2.dist-info/entry_points.txt
testing_project-0.1.2.dist-info/top_level.txt
testing_project-0.1.2.dist-info/RECORD
