Metadata-Version: 2.1
Name: testing-project
Version: 0.1.2
Summary: Project to show cookiecutter and release procedure
Home-page: https://github.com/ellesmith88/testing_project
Author: Elle Smith
Author-email: eleanor.smith@stfc.ac.uk
License: BSD - see LICENSE file in top-level package directory
Keywords: testing_project
Platform: UNKNOWN
Classifier: Development Status :: 5 - Production/Stable
Classifier: Environment :: Console
Classifier: Environment :: Web Environment
Classifier: Intended Audience :: End Users/Desktop
Classifier: Intended Audience :: Developers
Classifier: Intended Audience :: System Administrators
Classifier: Intended Audience :: Science/Research
Classifier: License :: OSI Approved :: BSD License
Classifier: Natural Language :: English
Classifier: Operating System :: Microsoft :: Windows
Classifier: Operating System :: POSIX :: Linux
Classifier: Programming Language :: Python
Classifier: Programming Language :: Python :: 3
Classifier: Programming Language :: Python :: 3.5
Classifier: Programming Language :: Python :: 3.6
Classifier: Programming Language :: Python :: 3.7
Classifier: Programming Language :: Python :: 3.8
Classifier: Topic :: Security
Classifier: Topic :: Internet
Classifier: Topic :: Scientific/Engineering
Classifier: Topic :: System :: Distributed Computing
Classifier: Topic :: System :: Systems Administration :: Authentication/Directory
Classifier: Topic :: Software Development :: Libraries :: Python Modules
Requires-Python: >=3.6
Provides-Extra: dev
Requires-Dist: pip (==19.2.3) ; extra == 'dev'
Requires-Dist: bump2version (==0.5.11) ; extra == 'dev'
Requires-Dist: wheel (==0.33.6) ; extra == 'dev'
Requires-Dist: watchdog (==0.9.0) ; extra == 'dev'
Requires-Dist: flake8 (==3.7.8) ; extra == 'dev'
Requires-Dist: tox (==3.14.0) ; extra == 'dev'
Requires-Dist: coverage (==4.5.4) ; extra == 'dev'
Requires-Dist: Sphinx (==1.8.5) ; extra == 'dev'
Requires-Dist: twine (==1.14.0) ; extra == 'dev'
Requires-Dist: pre-commit (==2.8.2) ; extra == 'dev'
Requires-Dist: pytest (==4.6.5) ; extra == 'dev'
Requires-Dist: pytest-runner (==5.1) ; extra == 'dev'
Provides-Extra: docs
Requires-Dist: sphinx ; extra == 'docs'
Requires-Dist: sphinx-rtd-theme ; extra == 'docs'
Requires-Dist: nbsphinx ; extra == 'docs'
Requires-Dist: pandoc ; extra == 'docs'
Requires-Dist: ipython ; extra == 'docs'
Requires-Dist: ipykernel ; extra == 'docs'
Requires-Dist: jupyter-client ; extra == 'docs'
